odc/geom/__init__.py
odc/geom/_version.py
odc_geom-0.2.0a0.dist-info/METADATA
odc_geom-0.2.0a0.dist-info/WHEEL
odc_geom-0.2.0a0.dist-info/top_level.txt
odc_geom-0.2.0a0.dist-info/RECORD
