Metadata-Version: 2.1
Name: odc-geom
Version: 0.2.0a0
Summary: Miscellaneous Geometry helper methods
Home-page: https://github.com/opendatacube/odc-tools/
Author: Open Data Cube
Author-email: 
Maintainer: Open Data Cube
Maintainer-email: 
License: Apache License 2.0
Platform: any
Requires-Python: >=3.6
Requires-Dist: affine
Requires-Dist: datacube
